lamindb_setup/__init__.py
lamindb_setup/_cache.py
lamindb_setup/_check.py
lamindb_setup/_check_setup.py
lamindb_setup/_connect_instance.py
lamindb_setup/_delete.py
lamindb_setup/_disconnect.py
lamindb_setup/_django.py
lamindb_setup/_entry_points.py
lamindb_setup/_init_instance.py
lamindb_setup/_migrate.py
lamindb_setup/_register_instance.py
lamindb_setup/_schema.py
lamindb_setup/_schema_metadata.py
lamindb_setup/_set_managed_storage.py
lamindb_setup/_setup_user.py
lamindb_setup/_silence_loggers.py
lamindb_setup/errors.py
lamindb_setup/io.py
lamindb_setup/py.typed
lamindb_setup/types.py
lamindb_setup/core/__init__.py
lamindb_setup/core/_aws_options.py
lamindb_setup/core/_aws_storage.py
lamindb_setup/core/_clone.py
lamindb_setup/core/_deprecated.py
lamindb_setup/core/_docs.py
lamindb_setup/core/_hub_client.py
lamindb_setup/core/_hub_core.py
lamindb_setup/core/_hub_crud.py
lamindb_setup/core/_hub_utils.py
lamindb_setup/core/_private_django_api.py
lamindb_setup/core/_settings.py
lamindb_setup/core/_settings_instance.py
lamindb_setup/core/_settings_load.py
lamindb_setup/core/_settings_save.py
lamindb_setup/core/_settings_storage.py
lamindb_setup/core/_settings_store.py
lamindb_setup/core/_settings_user.py
lamindb_setup/core/_setup_bionty_sources.py
lamindb_setup/core/cloud_sqlite_locker.py
lamindb_setup/core/django.py
lamindb_setup/core/exceptions.py
lamindb_setup/core/hashing.py
lamindb_setup/core/lamin.db.gz
lamindb_setup/core/types.py
lamindb_setup/core/upath.py
lamindb_setup-1.19.0.dist-info/LICENSE
lamindb_setup-1.19.0.dist-info/WHEEL
lamindb_setup-1.19.0.dist-info/METADATA
lamindb_setup-1.19.0.dist-info/RECORD
